daceypy/DA_utils.py
daceypy/RK.py
daceypy/_ADS.py
daceypy/_ADSintegrator.py
daceypy/_DA.py
daceypy/_DACEException.py
daceypy/_Monomial.py
daceypy/_PrettyType.py
daceypy/__init__.py
daceypy/_array.py
daceypy/_compiledDA.py
daceypy/_integrator.py
daceypy/_version.py
daceypy/core.py
daceypy/get_platform.py
daceypy/op.py
daceypy/op.pyi
daceypy/lib/dace_darwin-arm64.dylib
daceypy/lib/dace_darwin-x86_64.dylib
daceypy/lib/dace_linux-aarch64.so
daceypy/lib/dace_linux-i686.so
daceypy/lib/dace_linux-x86_64.so
daceypy/lib/dace_windows-arm64.dll
daceypy/lib/dace_windows-x64.dll
daceypy/lib/dace_windows-x86.dll
daceypy-1.3.0.dist-info/METADATA
daceypy-1.3.0.dist-info/WHEEL
daceypy-1.3.0.dist-info/top_level.txt
daceypy-1.3.0.dist-info/RECORD
