Metadata-Version: 2.4
Name: daceypy
Version: 1.3.0
Summary: Python wrapper of DACE, the Differential Algebra Computational Toolbox.
Home-page: https://github.com/giovannipurpura/daceypy
Author: Giovanni Purpura
License: Apache-2.0
Classifier: Development Status :: 5 - Production/Stable
Classifier: Natural Language :: English
Classifier: Topic :: Scientific/Engineering
Classifier: License :: OSI Approved :: Apache Software License
Classifier: Programming Language :: Python :: 3.7
Classifier: Programming Language :: Python :: 3.8
Classifier: Programming Language :: Python :: 3.9
Classifier: Programming Language :: Python :: 3.10
Classifier: Programming Language :: Python :: 3.11
Classifier: Programming Language :: Python :: 3.12
Classifier: Programming Language :: Python :: 3.13
Classifier: Programming Language :: Python :: 3.14
Classifier: Operating System :: POSIX :: Linux
Classifier: Operating System :: Microsoft :: Windows
Classifier: Operating System :: MacOS :: MacOS X
Requires-Python: >=3.7
Requires-Dist: numpy>=1.20.0
